gpymusic/__init__.py
gpymusic/client.py
gpymusic/common.py
gpymusic/music_objects.py
gpymusic/nowplaying.py
gpymusic/songqueue.py
gpymusic/start.py
gpymusic/view.py
gpymusic/writer.py
gpymusic/config/config.json
gpymusic/config/mpv_input.conf
gpymusic-1.2.1.data/scripts/gpymusic
gpymusic-1.2.1.data/scripts/gpymusic-download-all
gpymusic-1.2.1.data/scripts/gpymusic-get-dev-id
gpymusic-1.2.1.data/scripts/gpymusic-oauth-login
gpymusic-1.2.1.data/scripts/gpymusic-setup
gpymusic-1.2.1.dist-info/DESCRIPTION.rst
gpymusic-1.2.1.dist-info/METADATA
gpymusic-1.2.1.dist-info/RECORD
gpymusic-1.2.1.dist-info/WHEEL
gpymusic-1.2.1.dist-info/metadata.json
gpymusic-1.2.1.dist-info/top_level.txt
