Metadata-Version: 2.0
Name: gpymusic
Version: 1.2.1
Summary: A simple TUI client for Google Play Music
Home-page: https://github.com/christopher-dG/gpymusic
Author: Chris de Graaf
Author-email: chrisadegraaf@gmail.com
License: MIT
Keywords: terminal music streaming
Platform: UNKNOWN
Classifier: Development Status :: 4 - Beta
Classifier: License :: OSI Approved :: MIT License
Classifier: Environment :: Console :: Curses
Classifier: Intended Audience :: Developers
Classifier: Intended Audience :: End Users/Desktop
Classifier: Operating System :: Unix
Classifier: Topic :: Multimedia :: Sound/Audio :: Players
Classifier: Programming Language :: Python :: 3.4
Classifier: Programming Language :: Python :: 3.5
Classifier: Programming Language :: Python :: 3.6
Classifier: Programming Language :: Python :: 3 :: Only
Requires-Dist: gmusicapi
